pdf_crop/__init__.py
pdf_crop/__main__.py
pdf_crop/crop_base.py
pdf_crop/crop_pymupdf.py
pdf_crop/helper.py
pdf_crop-0.0.21.dist-info/METADATA
pdf_crop-0.0.21.dist-info/WHEEL
pdf_crop-0.0.21.dist-info/entry_points.txt
pdf_crop-0.0.21.dist-info/top_level.txt
pdf_crop-0.0.21.dist-info/zip-safe
pdf_crop-0.0.21.dist-info/RECORD
