Metadata-Version: 2.1
Name: pdf-crop
Version: 0.0.21
Summary: A commandline tool to crop a PDF into sub-PDFs
Home-page: https://www.niuwei.info
Author: wniu99
Author-email: niuwei95@gmail.com
License: FreeBSD
Keywords: PDF,Crop
Platform: UNKNOWN
Requires-Dist: pymupdf
Requires-Dist: imageio
Requires-Dist: rich
Requires-Dist: numpy
